aws_deepracer_control_v2/__init__.py
aws_deepracer_control_v2/aws_deepracer_control_v2.py
aws_deepracer_control_v2-0.1.5.dist-info/LICENSE
aws_deepracer_control_v2-0.1.5.dist-info/METADATA
aws_deepracer_control_v2-0.1.5.dist-info/WHEEL
aws_deepracer_control_v2-0.1.5.dist-info/top_level.txt
aws_deepracer_control_v2-0.1.5.dist-info/RECORD
