Metadata-Version: 2.1
Name: aws-deepracer-control-v2
Version: 0.1.5
Summary: aws_deepracer_control_v2 is a fork of awsdeepracer_control from lshw54
Home-page: https://github.com/jacobcantwell/aws_deepracer_control_v2
Author: jacobcantwell
Author-email: jacob.cantwell.deepracer@gmail.com
License: MIT
Project-URL: Bug Tracker, https://github.com/jacobcantwell/aws_deepracer_control_v2/issues
Platform: UNKNOWN
Classifier: Programming Language :: Python :: 3
Classifier: License :: OSI Approved :: MIT License
Classifier: Operating System :: OS Independent
Requires-Python: >=3.6
License-File: LICENSE
Requires-Dist: beautifulsoup4 (>=4.8.2)
Requires-Dist: bs4 (>=0.0.1)
Requires-Dist: lxml (>=4.4.2)
Requires-Dist: PyYAML (>=5.3)
Requires-Dist: requests (>=2.22.0)
Requires-Dist: requests-toolbelt (>=0.9.1)
Requires-Dist: urllib3 (>=1.25.8)
